{"ScheduledType":"flow","GUID":"b3c466f7-0ce4-4feb-a141-f61e385a4970","Name":"Stage 1 - Instruction Decode","Description":"","Labels":null,"Schedule":"* * * * *","Timezone":"","Disabled":false,"Duration":0,"Flow":"{\"id\":\"gravwell@0.0.1\",\"nodes\":{\"11\":{\"id\":11,\"name\":\"RunQuery\",\"inputs\":{\"in\":{\"connections\":[{\"node\":104,\"output\":\"out\",\"data\":{}}]}},\"outputs\":{\"out\":{\"connections\":[{\"node\":12,\"input\":\"in\",\"data\":{}}]}},\"data\":{\"querystring\":{\"type\":\"Constant\",\"value\":\"dump -r pipeline0\\n| eval ( \\n   opcode = (int(instruction) & 0xfc000000) >> 26; \\n   rs = (int(instruction) & 0x03b00000) >> 21; \\n   rt = (int(instruction) & 0x001f0000) >> 16 ; \\n   imm = int(instruction) & 0x0000ffff; \\n   addr = int(instruction) & 0x03ffffff \\n)\\n| table opcode rt rs imm addr instruction\"},\"duration\":{\"type\":\"Constant\",\"value\":\"PT1H\"},\"name\":{\"type\":\"Constant\",\"value\":\"decodeSearch\"},\"__meta\":{\"nickname\":null,\"notes\":null,\"inputs\":[],\"values\":{\"querystring\":{\"type\":{\"kind\":\"string:query\"},\"value\":\"dump -r pipeline0\\n| eval ( \\n   opcode = (int(instruction) & 0xfc000000) >> 26; \\n   rs = (int(instruction) & 0x03b00000) >> 21; \\n   rt = (int(instruction) & 0x001f0000) >> 16 ; \\n   imm = int(instruction) & 0x0000ffff; \\n   addr = int(instruction) & 0x03ffffff \\n)\\n| table opcode rt rs imm addr instruction\"},\"duration\":{\"type\":{\"kind\":\"string:isoduration\",\"default\":\"PT1H\"},\"value\":\"PT1H\"},\"name\":{\"type\":{\"kind\":\"string\",\"default\":\"search\"},\"value\":\"decodeSearch\"}}}},\"position\":[320,256]},\"12\":{\"id\":12,\"name\":\"GetTableResults\",\"inputs\":{\"in\":{\"connections\":[{\"node\":11,\"output\":\"out\",\"data\":{}}]}},\"outputs\":{\"out\":{\"connections\":[{\"node\":13,\"input\":\"in\",\"data\":{}}]}},\"data\":{\"search\":{\"type\":\"Variable\",\"value\":\"decodeSearch\"},\"count\":{\"type\":\"Constant\",\"value\":1},\"name\":{\"type\":\"Constant\",\"value\":\"decoded\"},\"__meta\":{\"inputs\":[],\"values\":{\"search\":{\"type\":{\"kind\":\"variable\"},\"value\":\"decodeSearch\"},\"count\":{\"type\":{\"kind\":\"int\"},\"value\":1},\"name\":{\"type\":{\"kind\":\"string\",\"default\":\"tableResults\"},\"value\":\"decoded\"}}}},\"position\":[576,256]},\"13\":{\"id\":13,\"name\":\"Template\",\"inputs\":{\"in\":{\"connections\":[{\"node\":12,\"output\":\"out\",\"data\":{}}]}},\"outputs\":{\"out\":{\"connections\":[{\"node\":14,\"input\":\"in\",\"data\":{}}]}},\"data\":{\"template\":{\"type\":\"Constant\",\"value\":\"dump -r pipeline1 | enrich -o opcode {{ index .decoded.Data 0 0 }} rt {{ index .decoded.Data 0 1 }} rs {{ index .decoded.Data 0 2 }} imm {{ index .decoded.Data 0 3 }} addr {{ index .decoded.Data 0 4 }} | table -save pipeline1 opcode rt rs imm addr\"},\"name\":{\"type\":\"Constant\",\"value\":\"pipeline1Write\"},\"__meta\":{\"nickname\":null,\"notes\":null,\"inputs\":[],\"values\":{\"template\":{\"type\":{\"kind\":\"string:longtext\"},\"value\":\"dump -r pipeline1 | enrich -o opcode {{ index .decoded.Data 0 0 }} rt {{ index .decoded.Data 0 1 }} rs {{ index .decoded.Data 0 2 }} imm {{ index .decoded.Data 0 3 }} addr {{ index .decoded.Data 0 4 }} | table -save pipeline1 opcode rt rs imm addr\"},\"name\":{\"type\":{\"kind\":\"string\",\"default\":\"templateOutput\"},\"value\":\"pipeline1Write\"}}}},\"position\":[880,256]},\"14\":{\"id\":14,\"name\":\"RunQuery\",\"inputs\":{\"in\":{\"connections\":[{\"node\":13,\"output\":\"out\",\"data\":{}}]}},\"outputs\":{\"out\":{\"connections\":[]}},\"data\":{\"querystring\":{\"type\":\"Variable\",\"value\":\"pipeline1Write\"},\"duration\":{\"type\":\"Constant\",\"value\":\"PT1H\"},\"name\":{\"type\":\"Constant\",\"value\":\"search\"},\"__meta\":{\"inputs\":[],\"values\":{\"querystring\":{\"type\":{\"kind\":\"variable\"},\"value\":\"pipeline1Write\"},\"duration\":{\"type\":{\"kind\":\"string:isoduration\",\"default\":\"PT1H\"},\"value\":\"PT1H\"},\"name\":{\"type\":{\"kind\":\"string\",\"default\":\"search\"},\"value\":\"search\"}}}},\"position\":[1152,256]},\"104\":{\"id\":104,\"name\":\"Sleep\",\"inputs\":{\"in\":{\"connections\":[]}},\"outputs\":{\"out\":{\"connections\":[{\"node\":11,\"input\":\"in\",\"data\":{}}]}},\"data\":{\"sleep\":{\"type\":\"Constant\",\"value\":10},\"__meta\":{\"nickname\":null,\"notes\":null,\"inputs\":[],\"values\":{\"sleep\":{\"type\":{\"kind\":\"int\"},\"value\":10}}}},\"position\":[64,256]}}}"}